django_postgres_unlimited_varchar.py
django_postgres_unlimited_varchar-1.1.2.dist-info/WHEEL
django_postgres_unlimited_varchar-1.1.2.dist-info/METADATA
django_postgres_unlimited_varchar-1.1.2.dist-info/RECORD
