Metadata-Version: 2.1
Name: django-postgres-unlimited-varchar
Version: 1.1.2
Summary: A tiny app adding support unlimited varchar fields in Django/Postgres.
Author: Jacob Kaplan-Moss
Author-email: jacob@jacobian.org
Requires-Python: >=3.6,<4.0
Classifier: Programming Language :: Python :: 3
Classifier: Programming Language :: Python :: 3.10
Classifier: Programming Language :: Python :: 3.6
Classifier: Programming Language :: Python :: 3.7
Classifier: Programming Language :: Python :: 3.8
Classifier: Programming Language :: Python :: 3.9
Requires-Dist: django (>=2,<5)
